flake8_force_keyword_arguments/__init__.py
flake8_force_keyword_arguments/checker.py
flake8_force_keyword_arguments/py.typed
flake8_force_keyword_arguments/util.py
flake8_force_keyword_arguments-2.0.0.dist-info/LICENSE
flake8_force_keyword_arguments-2.0.0.dist-info/METADATA
flake8_force_keyword_arguments-2.0.0.dist-info/WHEEL
flake8_force_keyword_arguments-2.0.0.dist-info/entry_points.txt
flake8_force_keyword_arguments-2.0.0.dist-info/RECORD
