Metadata-Version: 2.1
Name: flake8-force-keyword-arguments
Version: 2.0.0
Summary: A flake8 extension that is looking for function calls and forces to use keyword arguments if there are more than X arguments
Home-page: https://github.com/isac322/flake8-force-keyword-arguments
License: MIT
Author: Viktor Chaptsev
Author-email: viktor@chaptsev.ru
Maintainer: Byeonghoon Yoo
Maintainer-email: bh322yoo@gmail.com
Requires-Python: >=3.8.1,<4.0.0
Classifier: Development Status :: 4 - Beta
Classifier: Environment :: Console
Classifier: Framework :: Flake8
Classifier: Intended Audience :: Developers
Classifier: License :: OSI Approved :: MIT License
Classifier: Natural Language :: English
Classifier: Programming Language :: Python :: 3
Classifier: Programming Language :: Python :: 3.9
Classifier: Programming Language :: Python :: 3.10
Classifier: Programming Language :: Python :: 3.11
Classifier: Programming Language :: Python :: 3.12
Classifier: Programming Language :: Python :: 3.8
Classifier: Programming Language :: Python :: Implementation
Classifier: Programming Language :: Python :: Implementation :: CPython
Classifier: Programming Language :: Python :: Implementation :: PyPy
Classifier: Topic :: Software Development :: Libraries :: Python Modules
Classifier: Topic :: Software Development :: Quality Assurance
Requires-Dist: flake8 (>5)
Requires-Dist: marisa-trie (>=1,<2)
Project-URL: Repository, https://github.com/isac322/flake8-force-keyword-arguments
